rudaux/__init__.py
rudaux/assignment.py
rudaux/command_line.py
rudaux/commands.py
rudaux/course.py
rudaux/utils.py
rudaux-0.3.data/scripts/rudaux
rudaux-0.3.dist-info/METADATA
rudaux-0.3.dist-info/RECORD
rudaux-0.3.dist-info/WHEEL
rudaux-0.3.dist-info/top_level.txt
