Metadata-Version: 2.1
Name: rudaux
Version: 0.3
Summary: Canvas Course Management with JupyterHub & nbgrader.
Home-page: http://github.com/samhinshaw/rudaux
Author: Sam Hinshaw
Author-email: samuel.hinshaw@gmail.com
License: BSD
Platform: UNKNOWN
Requires-Dist: GitPython (==2.1.11)
Requires-Dist: nbgrader (==0.6.0.dev0)
Requires-Dist: pendulum (==2.0.3)
Requires-Dist: pytest (==3.6.3)
Requires-Dist: python-crontab (==2.3.4)
Requires-Dist: python-dateutil (==2.7.3)
Requires-Dist: pytzdata (==2018.5)
Requires-Dist: requests (==2.19.1)
Requires-Dist: terminaltables (==3.1.0)
Requires-Dist: tqdm (==4.23.4)
Requires-Dist: traitlets (==4.3.2)
